[{"line":1,"elements":[{"line":19,"name":"Get All Incidents for different params","description":"","id":"get-all-incidents-for-different-params","type":"scenario","keyword":"Scenario Outline","steps":[{"name":"def query = { sysparm_fields: 'number, sys_id,severity', category: 'software', sysparm_limit: 2 }","result":{"duration":98064200,"status":"passed"},"match":{"location":"karate","arguments":[]},"keyword":"*","line":6,"doc_string":{"content_type":"","value":"12:21:52.090 skipping bootstrap configuration: could not find or read file: classpath:karate-config.js","line":6}},{"name":"print query","result":{"duration":755200,"status":"passed"},"match":{"location":"karate","arguments":[]},"keyword":"*","line":7,"doc_string":{"content_type":"","value":"12:21:52.201 [print] {\n  \"sysparm_fields\": \"number, sys_id,severity\",\n  \"category\": \"software\",\n  \"sysparm_limit\": 2\n}","line":7}},{"name":"url 'https:\/\/dev49243.service-now.com\/api\/now\/table\/incident'","result":{"duration":3157600,"status":"passed"},"match":{"location":"karate","arguments":[]},"keyword":"Given","line":9},{"name":"header Authorization = call read('basic-auth.js') { username: 'admin', password: 'Tuna@123' }","result":{"duration":79409400,"status":"passed"},"match":{"location":"karate","arguments":[]},"keyword":"And","line":10},{"name":"params query","result":{"duration":338800,"status":"passed"},"match":{"location":"karate","arguments":[]},"keyword":"And","line":11},{"name":"method get","result":{"duration":4213046300,"status":"passed"},"match":{"location":"karate","arguments":[]},"keyword":"And","line":12,"doc_string":{"content_type":"","value":"12:21:53.255 request:\n1 > GET https:\/\/dev49243.service-now.com\/api\/now\/table\/incident?sysparm_fields=number%2C+sys_id%2Cseverity&category=software&sysparm_limit=2\n1 > Accept-Encoding: gzip,deflate\n1 > Authorization: Basic YWRtaW46VHVuYUAxMjM=\n1 > Connection: Keep-Alive\n1 > Host: dev49243.service-now.com\n1 > User-Agent: Apache-HttpClient\/4.5.11 (Java\/1.8.0_171)\n\n12:21:56.509 response time in milliseconds: 2955.46\n1 < 200\n1 < Cache-control: no-cache,no-store,must-revalidate,max-age=-1\n1 < Content-Type: application\/json;charset=UTF-8\n1 < Date: Sat, 02 May 2020 06:51:56 GMT\n1 < Expires: 0\n1 < Link: <https:\/\/dev49243.service-now.com\/api\/now\/table\/incident?sysparm_fields=number%2C+sys_id%2Cseverity&category=software&sysparm_limit=2&sysparm_offset=0>;rel=\"first\",<https:\/\/dev49243.service-now.com\/api\/now\/table\/incident?sysparm_fields=number%2C+sys_id%2Cseverity&category=software&sysparm_limit=2&sysparm_offset=2>;rel=\"next\",<https:\/\/dev49243.service-now.com\/api\/now\/table\/incident?sysparm_fields=number%2C+sys_id%2Cseverity&category=software&sysparm_limit=2&sysparm_offset=28>;rel=\"last\"\n1 < Pragma: no-store,no-cache\n1 < Server: ServiceNow\n1 < Set-Cookie: [JSESSIONID=243E192A9BCE0FD6B02F565C1BFBFCE5; Path=\/; HttpOnly;Secure, glide_user=; Max-Age=0; Expires=Thu, 01-Jan-1970 00:00:10 GMT; Path=\/; HttpOnly;Secure, glide_user_session=; Max-Age=0; Expires=Thu, 01-Jan-1970 00:00:10 GMT; Path=\/; HttpOnly;Secure, glide_user_route=glide.7470a14fdac8b492f6ea54c2b7b9cf7f; Max-Age=2147483647; Expires=Thu, 20-May-2088 10:06:03 GMT; Path=\/; HttpOnly;Secure, glide_session_store=3B02D5112F6010100510D6AB2799B6D5; Max-Age=1800; Expires=Sat, 02-May-2020 07:21:56 GMT; Path=\/; HttpOnly;Secure, BIGipServerpool_dev49243=2458146826.38974.0000; path=\/; Httponly; Secure]\n1 < Strict-Transport-Security: max-age=63072000; includeSubDomains\n1 < Transfer-Encoding: chunked\n1 < X-Is-Logged-In: true\n1 < X-Total-Count: 29\n1 < X-Transaction-ID: 7f02d5112f60\n{\"result\":[{\"severity\":\"3\",\"number\":\"INC0000019\",\"sys_id\":\"46e8219ba9fe1981013806b6e04fed06\"},{\"severity\":\"3\",\"number\":\"INC0000027\",\"sys_id\":\"46f4f4dfa9fe198100063e60278f76ec\"}]}","line":12}},{"name":"status 200","result":{"duration":8300,"status":"passed"},"match":{"location":"karate","arguments":[]},"keyword":"Then","line":13},{"name":"match header Content-Type contains 'application\/json'","result":{"duration":2460800,"status":"passed"},"match":{"location":"karate","arguments":[]},"keyword":"And","line":14},{"name":"print response","result":{"duration":507900,"status":"passed"},"match":{"location":"karate","arguments":[]},"keyword":"Then","line":15,"doc_string":{"content_type":"","value":"12:21:56.513 [print] {\n  \"result\": [\n    {\n      \"severity\": \"3\",\n      \"number\": \"INC0000019\",\n      \"sys_id\": \"46e8219ba9fe1981013806b6e04fed06\"\n    },\n    {\n      \"severity\": \"3\",\n      \"number\": \"INC0000027\",\n      \"sys_id\": \"46f4f4dfa9fe198100063e60278f76ec\"\n    }\n  ]\n}","line":15}}]},{"line":20,"name":"Get All Incidents for different params","description":"","id":"get-all-incidents-for-different-params","type":"scenario","keyword":"Scenario Outline","steps":[{"name":"def query = { sysparm_fields: 'number,severity', category: 'inquiry', sysparm_limit: 1 }","result":{"duration":94883000,"status":"passed"},"match":{"location":"karate","arguments":[]},"keyword":"*","line":6,"doc_string":{"content_type":"","value":"12:21:52.090 skipping bootstrap configuration: could not find or read file: classpath:karate-config.js","line":6}},{"name":"print query","result":{"duration":336600,"status":"passed"},"match":{"location":"karate","arguments":[]},"keyword":"*","line":7,"doc_string":{"content_type":"","value":"12:21:52.201 [print] {\n  \"sysparm_fields\": \"number,severity\",\n  \"category\": \"inquiry\",\n  \"sysparm_limit\": 1\n}","line":7}},{"name":"url 'https:\/\/dev49243.service-now.com\/api\/now\/table\/incident'","result":{"duration":1873200,"status":"passed"},"match":{"location":"karate","arguments":[]},"keyword":"Given","line":9},{"name":"header Authorization = call read('basic-auth.js') { username: 'admin', password: 'Tuna@123' }","result":{"duration":77815300,"status":"passed"},"match":{"location":"karate","arguments":[]},"keyword":"And","line":10},{"name":"params query","result":{"duration":336500,"status":"passed"},"match":{"location":"karate","arguments":[]},"keyword":"And","line":11},{"name":"method get","result":{"duration":4212962000,"status":"passed"},"match":{"location":"karate","arguments":[]},"keyword":"And","line":12,"doc_string":{"content_type":"","value":"12:21:53.255 request:\n1 > GET https:\/\/dev49243.service-now.com\/api\/now\/table\/incident?sysparm_fields=number%2Cseverity&category=inquiry&sysparm_limit=1\n1 > Accept-Encoding: gzip,deflate\n1 > Authorization: Basic YWRtaW46VHVuYUAxMjM=\n1 > Connection: Keep-Alive\n1 > Host: dev49243.service-now.com\n1 > User-Agent: Apache-HttpClient\/4.5.11 (Java\/1.8.0_171)\n\n12:21:56.504 response time in milliseconds: 2955.91\n1 < 200\n1 < Cache-control: no-cache,no-store,must-revalidate,max-age=-1\n1 < Content-Type: application\/json;charset=UTF-8\n1 < Date: Sat, 02 May 2020 06:51:56 GMT\n1 < Expires: 0\n1 < Link: <https:\/\/dev49243.service-now.com\/api\/now\/table\/incident?sysparm_fields=number%2Cseverity&category=inquiry&sysparm_limit=1&sysparm_offset=0>;rel=\"first\",<https:\/\/dev49243.service-now.com\/api\/now\/table\/incident?sysparm_fields=number%2Cseverity&category=inquiry&sysparm_limit=1&sysparm_offset=-1>;rel=\"prev\",<https:\/\/dev49243.service-now.com\/api\/now\/table\/incident?sysparm_fields=number%2Cseverity&category=inquiry&sysparm_limit=1&sysparm_offset=1>;rel=\"next\",<https:\/\/dev49243.service-now.com\/api\/now\/table\/incident?sysparm_fields=number%2Cseverity&category=inquiry&sysparm_limit=1&sysparm_offset=456>;rel=\"last\"\n1 < Pragma: no-store,no-cache\n1 < Server: ServiceNow\n1 < Set-Cookie: [JSESSIONID=89C38A39037F18634423B800204FA0FF; Path=\/; HttpOnly;Secure, glide_user=; Max-Age=0; Expires=Thu, 01-Jan-1970 00:00:10 GMT; Path=\/; HttpOnly;Secure, glide_user_session=; Max-Age=0; Expires=Thu, 01-Jan-1970 00:00:10 GMT; Path=\/; HttpOnly;Secure, glide_user_route=glide.7470a14fdac8b492f6ea54c2b7b9cf7f; Max-Age=2147483647; Expires=Thu, 20-May-2088 10:06:03 GMT; Path=\/; HttpOnly;Secure, glide_session_store=370219912FA010100510D6AB2799B6A8; Max-Age=1800; Expires=Sat, 02-May-2020 07:21:56 GMT; Path=\/; HttpOnly;Secure, BIGipServerpool_dev49243=2458146826.38974.0000; path=\/; Httponly; Secure]\n1 < Strict-Transport-Security: max-age=63072000; includeSubDomains\n1 < Transfer-Encoding: chunked\n1 < X-Is-Logged-In: true\n1 < X-Total-Count: 457\n1 < X-Transaction-ID: 7b0219912fa0\n{\"result\":[{\"severity\":\"3\",\"number\":\"INC0000015\"}]}","line":12}},{"name":"status 200","result":{"duration":13500,"status":"passed"},"match":{"location":"karate","arguments":[]},"keyword":"Then","line":13},{"name":"match header Content-Type contains 'application\/json'","result":{"duration":5568500,"status":"passed"},"match":{"location":"karate","arguments":[]},"keyword":"And","line":14},{"name":"print response","result":{"duration":507800,"status":"passed"},"match":{"location":"karate","arguments":[]},"keyword":"Then","line":15,"doc_string":{"content_type":"","value":"12:21:56.513 [print] {\n  \"result\": [\n    {\n      \"severity\": \"3\",\n      \"number\": \"INC0000015\"\n    }\n  ]\n}","line":15}}]}],"name":"karate\/getincidentsByParams.feature","description":"Incident Management","id":"incident-management","keyword":"Feature","uri":"karate\/getincidentsByParams.feature"}]