[{"line":1,"elements":[{"line":12,"name":"Delete Incident","description":"","id":"delete-incident","type":"scenario","keyword":"Scenario Outline","steps":[{"name":"url 'https:\/\/dev49243.service-now.com\/api\/now\/table\/incident\/89d79ec12f2410100510d6ab2799b676'","result":{"duration":4204200,"status":"passed"},"match":{"location":"karate","arguments":[]},"keyword":"Given","line":5,"doc_string":{"content_type":"","value":"12:21:52.090 skipping bootstrap configuration: could not find or read file: classpath:karate-config.js","line":5}},{"name":"header Authorization = call read('basic-auth.js') { username: 'admin', password: 'Tuna@123' }","result":{"duration":170242200,"status":"passed"},"match":{"location":"karate","arguments":[]},"keyword":"And","line":6},{"name":"method delete","result":{"duration":4264606100,"status":"passed"},"match":{"location":"karate","arguments":[]},"keyword":"When","line":7,"doc_string":{"content_type":"","value":"12:21:53.239 request:\n1 > DELETE https:\/\/dev49243.service-now.com\/api\/now\/table\/incident\/89d79ec12f2410100510d6ab2799b676\n1 > Accept-Encoding: gzip,deflate\n1 > Authorization: Basic YWRtaW46VHVuYUAxMjM=\n1 > Connection: Keep-Alive\n1 > Host: dev49243.service-now.com\n1 > User-Agent: Apache-HttpClient\/4.5.11 (Java\/1.8.0_171)\n\n12:21:56.557 response time in milliseconds: 2952.43\n1 < 404\n1 < Cache-control: no-cache,no-store,must-revalidate,max-age=-1\n1 < Content-Type: application\/json;charset=UTF-8\n1 < Date: Sat, 02 May 2020 06:51:56 GMT\n1 < Expires: 0\n1 < Pragma: no-store,no-cache\n1 < Server: ServiceNow\n1 < Set-Cookie: [JSESSIONID=0EE5DB4629E036AB23843866DA5283FB; Path=\/; HttpOnly;Secure, glide_user=; Max-Age=0; Expires=Thu, 01-Jan-1970 00:00:10 GMT; Path=\/; HttpOnly;Secure, glide_user_session=; Max-Age=0; Expires=Thu, 01-Jan-1970 00:00:10 GMT; Path=\/; HttpOnly;Secure, glide_user_route=glide.7470a14fdac8b492f6ea54c2b7b9cf7f; Max-Age=2147483647; Expires=Thu, 20-May-2088 10:06:03 GMT; Path=\/; HttpOnly;Secure, glide_session_store=370211DD2FE010100510D6AB2799B693; Max-Age=1800; Expires=Sat, 02-May-2020 07:21:56 GMT; Path=\/; HttpOnly;Secure, BIGipServerpool_dev49243=2458146826.38974.0000; path=\/; Httponly; Secure]\n1 < Strict-Transport-Security: max-age=63072000; includeSubDomains\n1 < Transfer-Encoding: chunked\n1 < X-Is-Logged-In: true\n1 < X-Transaction-ID: 7b0211dd2fe0\n{\"error\":{\"detail\":\"Record doesn't exist or ACL restricts the record retrieval\",\"message\":\"No Record found\"},\"status\":\"failure\"}","line":7}},{"name":"status 204","result":{"duration":407600,"error_message":"com.intuit.karate.exception.KarateException: deleteincident.feature:8 - status code was: 404, expected: 204, response time: 2952, url: https:\/\/dev49243.service-now.com\/api\/now\/table\/incident\/89d79ec12f2410100510d6ab2799b676, response: {\"error\":{\"detail\":\"Record doesn't exist or ACL restricts the record retrieval\",\"message\":\"No Record found\"},\"status\":\"failure\"}","status":"failed"},"match":{"location":"karate","arguments":[]},"keyword":"Then","line":8,"doc_string":{"content_type":"","value":"12:21:56.558 status code was: 404, expected: 204, response time: 2952, url: https:\/\/dev49243.service-now.com\/api\/now\/table\/incident\/89d79ec12f2410100510d6ab2799b676, response: {\"error\":{\"detail\":\"Record doesn't exist or ACL restricts the record retrieval\",\"message\":\"No Record found\"},\"status\":\"failure\"}","line":8}}]},{"line":13,"name":"Delete Incident","description":"","id":"delete-incident","type":"scenario","keyword":"Scenario Outline","steps":[{"name":"url 'https:\/\/dev49243.service-now.com\/api\/now\/table\/incident\/12f75a012fa410100510d6ab2799b637'","result":{"duration":3362800,"status":"passed"},"match":{"location":"karate","arguments":[]},"keyword":"Given","line":5,"doc_string":{"content_type":"","value":"12:21:56.519 skipping bootstrap configuration: could not find or read file: classpath:karate-config.js","line":5}},{"name":"header Authorization = call read('basic-auth.js') { username: 'admin', password: 'Tuna@123' }","result":{"duration":2598000,"status":"passed"},"match":{"location":"karate","arguments":[]},"keyword":"And","line":6},{"name":"method delete","result":{"duration":2584068400,"status":"passed"},"match":{"location":"karate","arguments":[]},"keyword":"When","line":7,"doc_string":{"content_type":"","value":"12:21:56.527 request:\n1 > DELETE https:\/\/dev49243.service-now.com\/api\/now\/table\/incident\/12f75a012fa410100510d6ab2799b637\n1 > Accept-Encoding: gzip,deflate\n1 > Authorization: Basic YWRtaW46VHVuYUAxMjM=\n1 > Connection: Keep-Alive\n1 > Host: dev49243.service-now.com\n1 > User-Agent: Apache-HttpClient\/4.5.11 (Java\/1.8.0_171)\n\n12:21:59.110 response time in milliseconds: 2195.19\n1 < 404\n1 < Cache-control: no-cache,no-store,must-revalidate,max-age=-1\n1 < Content-Type: application\/json;charset=UTF-8\n1 < Date: Sat, 02 May 2020 06:51:59 GMT\n1 < Expires: 0\n1 < Pragma: no-store,no-cache\n1 < Server: ServiceNow\n1 < Set-Cookie: [JSESSIONID=2A7475F1921A5499D6942FA2CF5B8707; Path=\/; HttpOnly;Secure, glide_user=; Max-Age=0; Expires=Thu, 01-Jan-1970 00:00:10 GMT; Path=\/; HttpOnly;Secure, glide_user_session=; Max-Age=0; Expires=Thu, 01-Jan-1970 00:00:10 GMT; Path=\/; HttpOnly;Secure, glide_user_route=glide.7470a14fdac8b492f6ea54c2b7b9cf7f; Max-Age=2147483647; Expires=Thu, 20-May-2088 10:06:06 GMT; Path=\/; HttpOnly;Secure, glide_session_store=E4125D192F2010100510D6AB2799B6E2; Max-Age=1800; Expires=Sat, 02-May-2020 07:21:59 GMT; Path=\/; HttpOnly;Secure, BIGipServerpool_dev49243=2458146826.38974.0000; path=\/; Httponly; Secure]\n1 < Strict-Transport-Security: max-age=63072000; includeSubDomains\n1 < Transfer-Encoding: chunked\n1 < X-Is-Logged-In: true\n1 < X-Transaction-ID: 2c125d192f20\n{\"error\":{\"detail\":\"Record doesn't exist or ACL restricts the record retrieval\",\"message\":\"No Record found\"},\"status\":\"failure\"}","line":7}},{"name":"status 204","result":{"duration":230400,"error_message":"com.intuit.karate.exception.KarateException: deleteincident.feature:8 - status code was: 404, expected: 204, response time: 2195, url: https:\/\/dev49243.service-now.com\/api\/now\/table\/incident\/12f75a012fa410100510d6ab2799b637, response: {\"error\":{\"detail\":\"Record doesn't exist or ACL restricts the record retrieval\",\"message\":\"No Record found\"},\"status\":\"failure\"}","status":"failed"},"match":{"location":"karate","arguments":[]},"keyword":"Then","line":8,"doc_string":{"content_type":"","value":"12:21:59.110 status code was: 404, expected: 204, response time: 2195, url: https:\/\/dev49243.service-now.com\/api\/now\/table\/incident\/12f75a012fa410100510d6ab2799b637, response: {\"error\":{\"detail\":\"Record doesn't exist or ACL restricts the record retrieval\",\"message\":\"No Record found\"},\"status\":\"failure\"}","line":8}}]}],"name":"karate\/deleteincident.feature","description":"Incident Management","id":"incident-management","keyword":"Feature","uri":"karate\/deleteincident.feature"}]